callbackable_sentence_transformers/__init__.py
callbackable_sentence_transformers/callbackable_sentence_transformers.py
callbackable_sentence_transformers-2024.0.0.dist-info/LICENSE
callbackable_sentence_transformers-2024.0.0.dist-info/METADATA
callbackable_sentence_transformers-2024.0.0.dist-info/WHEEL
callbackable_sentence_transformers-2024.0.0.dist-info/top_level.txt
callbackable_sentence_transformers-2024.0.0.dist-info/RECORD
