Metadata-Version: 2.1
Name: callbackable-sentence-transformers
Version: 2024.0.0
Summary: A simple package to add a new parameter for the SentenceTransformer class
Author-email: Cyrille Siouffi <cyrille.siouffi@protonmail.com>
Maintainer-email: Cyrille Siouffi <cyrille.siouffi@protonmail.com>
License: MIT License
Keywords: sentence_transformers,train,log
Classifier: Programming Language :: Python
Requires-Python: >=3.8
License-File: LICENSE
Requires-Dist: sentence-transformers
Requires-Dist: torch
Requires-Dist: tqdm
Requires-Dist: transformers
